orm_cloud/__init__.py
orm_cloud/configuration.py
orm_cloud/entity.py
orm_cloud/entity_decorator.py
orm_cloud/field_decorator.py
orm_cloud/request_router.py
orm_cloud/database_adapters/__init__.py
orm_cloud/database_adapters/database_adapter.py
orm_cloud/database_adapters/database_factory.py
orm_cloud/database_adapters/ms_sql_adapter.py
orm_cloud/database_adapters/lucene_parser/__init__.py
orm_cloud/database_adapters/lucene_parser/lucene_parser.py
orm_cloud/request_parsers/__init__.py
orm_cloud/request_parsers/api_gateway_request_parser.py
orm_cloud/response_formatters/__init__.py
orm_cloud/response_formatters/api_gateway_response_formatter.py
orm_cloud-1.0.1_alpha.5.dist-info/LICENSE
orm_cloud-1.0.1_alpha.5.dist-info/METADATA
orm_cloud-1.0.1_alpha.5.dist-info/WHEEL
orm_cloud-1.0.1_alpha.5.dist-info/top_level.txt
orm_cloud-1.0.1_alpha.5.dist-info/RECORD
