Metadata-Version: 2.1
Name: orm-cloud
Version: 1.0.1-alpha.5
Summary: An ORM solution for serverless cloud platforms
Home-page: https://github.com/gregchagnon/orm.cloud
Author: Gregory Chagnon
Author-email: greg@gregchagnon.io
License: Apache 2.0
Keywords: ORM,cloud,serverless
Platform: UNKNOWN
Classifier: Development Status :: 3 - Alpha
Classifier: Intended Audience :: Developers
Classifier: Topic :: Software Development :: Build Tools
Classifier: License :: OSI Approved :: Apache Software License
Classifier: Programming Language :: Python :: 3
Classifier: Programming Language :: Python :: 3.4
Classifier: Programming Language :: Python :: 3.5
Classifier: Programming Language :: Python :: 3.6
Classifier: Programming Language :: Python :: 3.7
Requires-Dist: pymssql
